{
  "users": [
    {
      "name": "user1",
      "email": "user1@outlook.com",
      "id": 1
    },
    {
      "name": "user2",
      "email": "user2@gmail.com",
      "id": 2
    },
    {
      "name": "user3",
      "email": "suer3",
      "id": 3
    },
    {
      "name": "user4",
      "email": "user4",
      "id": 4
    },
    {
      "name": "user5",
      "email": "user5",
      "id": 5
    },
    {
      "name": "user6",
      "email": "user6",
      "id": 6
    },
    {
      "name": "user7",
      "email": "user7",
      "id": 7
    },
    {
      "name": "user8",
      "email": "user8",
      "id": 8
    },
    {
      "name": "user9",
      "email": "user9",
      "id": 9
    },
    {
      "name": "user10",
      "email": "user10",
      "id": 10
    },
    {
      "name": "user11",
      "email": "user11",
      "id": 11
    }
  ]
}